{
    "text_block_list": [
        {
            "name": "Air Shakur",
            "text": "A mere quarter reduction in resistance coefficient...? Then reduce the distance by 5%――...Tch, as expected, totally useless."
        },
        {
            "name": "Agnes Tachyon",
            "text": "Oh-ho, Shakur, even today you line up numbers \nas always. Well well, quite impressive!"
        },
        {
            "name": "Air Shakur",
            "text": "Huh!? Are you picking a fight...?"
        },
        {
            "name": "Agnes Tachyon",
            "text": "No, really? I... just wondered whether within the numbers you believe in, there actually is an answer."
        },
        {
            "name": "Agnes Tachyon",
            "text": "What if the answer you seek isn’t in the numbers? What if spiritual or mental strength becomes the stronger factor over logic?"
        },
        {
            "name": "Agnes Tachyon",
            "text": "No matter how much you peel, you’ll never reach a seed forever! Even then you claim you find the seed in an onion!? Really!?"
        },
        {
            "name": "Air Shakur",
            "text": "...Hah? An onion is itself a bulb. There isn’t some seed. Stop twisting the argument."
        },
        {
            "name": "Agnes Tachyon",
            "text": "Ah-hahaha!! Yes, that was just a little jest!!"
        },
        {
            "name": "Agnes Tachyon",
            "text": "But by my jest, your mental seems to have shaken somewhat. If so, might there also be a similar effect in the race?"
        },
        {
            "name": "Air Shakur",
            "text": "I couldn’t care less. Seriously... you’re still as crazy as ever."
        }
    ]
}
